{
  "profileImage": "/images/efeeleprofile.webp",
  "profileAlt": "Photo of Fernando Aldair L칩pez Ponce (EFEELE) for the blog",
  "profileLink": "/about-me",
  "profileTitle": "Ingeniero Civil Industrial",
  "profileName": "Matias Pacheco Beltr치n",
  "github": "https://github.com/EFEELE/NeonMint",
  "githubText": "Do you like this blog's design?",
  "portfolioImage": "/images/portfolio.webp",
  "email": "matiaspachecob@gmail.com",
  "linkedin": "https://www.linkedin.com/in/efeele/",
  "instagram": "https://www.instagram.com/efeele.dev/",
  "youtube": "https://www.youtube.com/@efeeledev",
  "alias": "EFEELE",
  "contactSectionTitle": "Ready to take your idea to the next level?",
  "contactSectionSubtitle": "Let's work together.",
  "contactSectionButtonText": "Contact Me",
  "contactSectionButtonIcon": "paperplane",
  "techsTitle": "TECHS",
  "instagramIconName": "instagram",
  "youtubeIconName": "youtube",
  "githubIconName": "github",
  "linkedinIconName": "linkedin",
  "emailIconName": "envelope",
  "hobbies": [
    "Writing",
    "Camping",
    "Coffee",
    "Music",
    "Movies",
    "Board Games"
  ],
  "pageTitle": "Matias Pacheco Beltr치n | Ingeniero Civil Industrial",
  "pageDescription": "Is a modern, minimalist template crafted for developers and digital creatives.",
  "OGImage": {
    "url": "/images/imagedefault.webp",
    "alt": "Screenshot of a web portfolio with a modern and dark design. Featuring Fernando L칩pez, a Frontend Developer with 8 years of experience, highlighting his passion for development and technology. Includes contact sections, projects, and a technology stack with technologies like HTML5, JavaScript, TypeScript, Angular, Node.js, CSS, Tailwind, and more."
  }
}